lanote_core/__init__.py
lanote_core-0.0.5.dist-info/WHEEL
lanote_core-0.0.5.dist-info/METADATA
lanote_core-0.0.5.dist-info/RECORD
