Metadata-Version: 2.1
Name: lanote-core
Version: 0.0.5
Summary: 
License: Proprietary
Author: Viet Ho
Author-email: 4677759+VietHo@users.noreply.github.com
Requires-Python: >=3.8,<4.0
Classifier: License :: Other/Proprietary License
Classifier: Programming Language :: Python :: 3
Classifier: Programming Language :: Python :: 3.8
Classifier: Programming Language :: Python :: 3.9
Requires-Dist: Flask-Migrate (>=3.1.0,<4.0.0)
Requires-Dist: Flask-SQLAlchemy (>=2.5.1,<3.0.0)
Requires-Dist: psycopg2-binary (>=2.9.1,<3.0.0)
Requires-Dist: python-dotenv (>=0.19.1,<0.20.0)
